run_torch_model/__init__.py
run_torch_model/run_torch_model.py
run_torch_model/tools.py
run_torch_model-1.0.2.dist-info/LICENSE
run_torch_model-1.0.2.dist-info/METADATA
run_torch_model-1.0.2.dist-info/WHEEL
run_torch_model-1.0.2.dist-info/top_level.txt
run_torch_model-1.0.2.dist-info/RECORD
