Metadata-Version: 2.1
Name: run-torch-model
Version: 1.0.2
Summary: Package for training and evaluating neural network models made using pytorch
Home-page: https://github.com/chdre/run-torch-model
Author: Christer Dreierstad
Author-email: christerdr@outlook.com
License: UNKNOWN
Platform: UNKNOWN
Classifier: Programming Language :: Python :: 3
Classifier: License :: OSI Approved :: MIT License
Classifier: Operating System :: OS Independent
Requires-Python: >=3.6
License-File: LICENSE
Requires-Dist: torch
Requires-Dist: torchmetrics
Requires-Dist: scikit-learn
